writecondastat/__init__.py
writecondastat/condastat.py
writecondastat/py.typed
writecondastat/statdate.py
write_condastat-0.3.0.dist-info/LICENSE
write_condastat-0.3.0.dist-info/METADATA
write_condastat-0.3.0.dist-info/WHEEL
write_condastat-0.3.0.dist-info/top_level.txt
write_condastat-0.3.0.dist-info/RECORD
