Metadata-Version: 2.1
Name: write-condastat
Version: 0.3.0
Summary: write-condastat makes it easy to collect, filter and save conda statistics to csv files.
Home-page: https://github.com/veghdev/write-condastat
License: Apache 2.0
Project-URL: Documentation, https://github.com/veghdev/write-condastat
Project-URL: Source, https://github.com/veghdev/write-condastat
Project-URL: Tracker, https://github.com/veghdev/write-condastat/issues
Classifier: Programming Language :: Python :: 3
Classifier: License :: OSI Approved :: Apache Software License
Classifier: Operating System :: OS Independent
Classifier: Environment :: Console
Requires-Python: >=3.6
License-File: LICENSE
Requires-Dist: click ==8.1.7
Requires-Dist: cloudpickle ==3.0.0
Requires-Dist: dask ==2024.2.1
Requires-Dist: fsspec ==2024.3.1
Requires-Dist: importlib-metadata ==7.1.0
Requires-Dist: locket ==1.0.0
Requires-Dist: numpy ==1.26.4
Requires-Dist: packaging ==24.0
Requires-Dist: pandas ==2.2.2
Requires-Dist: partd ==1.4.1
Requires-Dist: python-dateutil ==2.9.0.post0
Requires-Dist: pytz ==2024.1
Requires-Dist: pyyaml ==6.0.1
Requires-Dist: six ==1.16.0
Requires-Dist: toolz ==0.12.1
Requires-Dist: tzdata ==2024.1
Requires-Dist: zipp ==3.18.1
